README.md
erulbpy.py
ruledata.py
setup.py
erulb_py.egg-info/PKG-INFO
erulb_py.egg-info/SOURCES.txt
erulb_py.egg-info/dependency_links.txt
erulb_py.egg-info/requires.txt
erulb_py.egg-info/top_level.txt
erulb_py.egg-info/zip-safe