Metadata-Version: 1.0
Name: erulb-py
Version: 0.0.3
Summary: ELB 3 python client
Home-page: UNKNOWN
Author: timfeirg
Author-email: timfeirg@icloud.com
License: UNKNOWN
Platform: UNKNOWN
